Metadata-Version: 1.1
Name: iotools
Version: 0.4.2
Summary: A wrapper for simple file IO to eliminate boilerplate.
Home-page: https://github.com/AbstractClass/IOTools/
Author: Connor MacLeod
Author-email: connor.macleod96@hotmail.ca
License: UNKNOWN
Download-URL: https://github.com/AbstractClass/IOTools/archive/0.4.tar.gz
Keywords: file,IO,csv,json
Platform: UNKNOWN
Classifier: Development Status :: 3 - Alpha
Classifier: License :: OSI Approved :: MIT License
Classifier: Programming Language :: Python :: 3.5
